aminocode/__init__.py
aminocode/aminocode.py
aminocode/encodefile.py
aminocode-1.0.1.dist-info/METADATA
aminocode-1.0.1.dist-info/WHEEL
aminocode-1.0.1.dist-info/top_level.txt
aminocode-1.0.1.dist-info/RECORD
