Metadata-Version: 2.1
Name: aminocode
Version: 1.0.1
Summary: The aminocode library can be used to encode texts written in natural language in a format based on amino acids
Home-page: UNKNOWN
Author: Diogo de Jesus Soares Machado
Author-email: diogomachado.bioinfo@gmail.com
License: UNKNOWN
Platform: UNKNOWN
Requires-Dist: numpy
Requires-Dist: unidecode
Requires-Dist: Biopython
